Classfile /Users/chengkai/IdeaProjects/myjava/src/main/java/com/kaesar/test/Demo1.class
  Last modified 2020-11-18; size 442 bytes
  MD5 checksum 8c0e464af40e39840208c51c89ee29a6
  Compiled from "Demo1.java"
public class com.kaesar.test.Demo1
  minor version: 0
  major version: 52
  flags: ACC_PUBLIC, ACC_SUPER
Constant pool:
   #1 = Methodref          #8.#19         // java/lang/Object."<init>":()V
   #2 = Class              #20            // com/kaesar/test/Demo1
   #3 = Methodref          #2.#19         // com/kaesar/test/Demo1."<init>":()V
   #4 = Methodref          #2.#21         // com/kaesar/test/Demo1.math:()I
   #5 = Class              #22            // java/lang/Thread
   #6 = Methodref          #5.#19         // java/lang/Thread."<init>":()V
   #7 = Methodref          #5.#23         // java/lang/Thread.start:()V
   #8 = Class              #24            // java/lang/Object
   #9 = Utf8               <init>
  #10 = Utf8               ()V
  #11 = Utf8               Code
  #12 = Utf8               LineNumberTable
  #13 = Utf8               math
  #14 = Utf8               ()I
  #15 = Utf8               main
  #16 = Utf8               ([Ljava/lang/String;)V
  #17 = Utf8               SourceFile
  #18 = Utf8               Demo1.java
  #19 = NameAndType        #9:#10         // "<init>":()V
  #20 = Utf8               com/kaesar/test/Demo1
  #21 = NameAndType        #13:#14        // math:()I
  #22 = Utf8               java/lang/Thread
  #23 = NameAndType        #25:#10        // start:()V
  #24 = Utf8               java/lang/Object
  #25 = Utf8               start
{
  public com.kaesar.test.Demo1();
    descriptor: ()V
    flags: ACC_PUBLIC
    Code:
      stack=1, locals=1, args_size=1
         0: aload_0
         1: invokespecial #1                  // Method java/lang/Object."<init>":()V
         4: return
      LineNumberTable:
        line 3: 0

  public int math();
    descriptor: ()I
    flags: ACC_PUBLIC
    Code:
      stack=2, locals=4, args_size=1
         0: iconst_1
         1: istore_1
         2: iconst_2
         3: istore_2
         4: iload_1
         5: iload_2
         6: iadd
         7: bipush        10
         9: imul
        10: istore_3
        11: iload_3
        12: ireturn
      LineNumberTable:
        line 5: 0
        line 6: 2
        line 7: 4
        line 8: 11

  public static void main(java.lang.String[]);
    descriptor: ([Ljava/lang/String;)V
    flags: ACC_PUBLIC, ACC_STATIC
    Code:
      stack=2, locals=2, args_size=1
         0: new           #2                  // class com/kaesar/test/Demo1
         3: dup
         4: invokespecial #3                  // Method "<init>":()V
         7: astore_1
         8: aload_1
         9: invokevirtual #4                  // Method math:()I
        12: pop
        13: new           #5                  // class java/lang/Thread
        16: dup
        17: invokespecial #6                  // Method java/lang/Thread."<init>":()V
        20: invokevirtual #7                  // Method java/lang/Thread.start:()V
        23: return
      LineNumberTable:
        line 12: 0
        line 13: 8
        line 14: 13
        line 15: 23
}
SourceFile: "Demo1.java"
